Workbook
Name Aporte: Planilha1!$C$19
Name patrimonio: Planilha1!$C$22
Name qtd_anos: Planilha1!$C$20
Name rendimento_carteira: Planilha1!$C$14
Name salario: Planilha1!$C$13
Name sugestao_investimento: Planilha1!$C$15
Name taxa: Planilha1!$C$21
Name Taxa_mensal: Planilha1!$C$20

Sheet Planilha1
B12: CONFIGURAÇÕES
B13: Salário | C13: 5000
B14: Rendimento carteira | C14: 0.01
B15: Sugestão de investimento | C15: =C13*30% -> 1500
B18: INVESTIMENTO MENSAL
B19: Quanto investir por mês? | C19: 500
B20: Por quantos anos? | C20: 5
B21: Taxa de rendimento mensal? | C21: 0.0108
B22: Patrimônio acumulado? | C22: =FV(taxa,qtd_anos*12,Aporte*-1) -> 41902.01
B23: Dividendos mensais? | C23: =C22*$C$14 -> 419.0201
B27: CENÁRIOS | D27: Dividendo
A28: 2 | B28: Quanto em 2 anos? | C28: =FV($C$21,$A28*12,$C$19*-1) -> 13615.432 | D28: =C28*$C$14 -> 136.15432
A29: 5 | B29: Quanto em 5 anos? | C29: =FV($C$21,$A29*12,$C$19*-1) -> 41902.01 | D29: =C29*$C$14 -> 419.0201
A30: 10 | B30: Quanto em 10 anos? | C30: =FV($C$21,$A30*12,$C$19*-1) -> 121728.83 | D30: =C30*$C$14 -> 1217.2883
A31: 20 | B31: Quanto em 20 anos? | C31: =FV($C$21,$A31*12,$C$19*-1) -> 563524.5 | D31: =C31*$C$14 -> 5635.245
A32: 30 | B32: Quanto em 30 anos? | C32: =FV($C$21,$A32*12,$C$19*-1) -> 2166952.4 | D32: =C32*$C$14 -> 21669.524
B36: Perfil | D36: Agressivo
B37: Valor a ser investido por mês | D37: =Aporte -> 500
B40: Tipo de FII | D40: Percentual sugerido | E40: Valores
B41: Papel | D41: =VLOOKUP($D$36&"-"&B41,Planilha2!$B:$E,4,FALSE) -> 0.5 | E41: =D41*$D$37 -> 250
B42: Tijolo | D42: =VLOOKUP($D$36&"-"&B42,Planilha2!$B:$E,4,FALSE) -> 0.1 | E42: =D42*$D$37 -> 50
B43: Híbridos | D43: =VLOOKUP($D$36&"-"&B43,Planilha2!$B:$E,4,FALSE) -> 0.05 | E43: =D43*$D$37 -> 25
B44: FOFs | D44: =VLOOKUP($D$36&"-"&B44,Planilha2!$B:$E,4,FALSE) -> 0.05 | E44: =D44*$D$37 -> 25
B45: Desenvolvimento | D45: =VLOOKUP($D$36&"-"&B45,Planilha2!$B:$E,4,FALSE) -> 0.2 | E45: =D45*$D$37 -> 100
B46: Hotelarias | D46: =VLOOKUP($D$36&"-"&B46,Planilha2!$B:$E,4,FALSE) -> 0.1 | E46: =D46*$D$37 -> 50
E47: =SUM(E41:E46) -> 500

Sheet Planilha2
B2: Chave | C2: Perfil | D2: Tipo de FII | E2: % | J2: %
B3: =$C$3&"-"&D3 -> Conservador-Papel | C3: Conservador | D3: Papel | E3: 0.3 | I3: Moderado-TIJOLO | J3: =VLOOKUP(I3,$B:$E,4,FALSE) -> 0.35
B4: =$C$3&"-"&D4 -> Conservador-Tijolo | C4: Conservador | D4: Tijolo | E4: 0.5
B5: =$C$3&"-"&D5 -> Conservador-Híbridos | C5: Conservador | D5: Híbridos | E5: 0.1
B6: =$C$3&"-"&D6 -> Conservador-FOFs | C6: Conservador | D6: FOFs | E6: 0.1
B7: =$C$3&"-"&D7 -> Conservador-Desenvolvimento | C7: Conservador | D7: Desenvolvimento | E7: 0
B8: =$C$3&"-"&D8 -> Conservador-Hotelarias | C8: Conservador | D8: Hotelarias | E8: 0
B9: =$C$9&"-"&D9 -> Moderado-Papel | C9: Moderado | D9: Papel | E9: 0.32
B10: =$C$9&"-"&D10 -> Moderado-Tijolo | C10: Moderado | D10: Tijolo | E10: 0.35
B11: =$C$9&"-"&D11 -> Moderado-Híbridos | C11: Moderado | D11: Híbridos | E11: 0.08
B12: =$C$9&"-"&D12 -> Moderado-FOFs | C12: Moderado | D12: FOFs | E12: 0.05
B13: =$C$9&"-"&D13 -> Moderado-Desenvolvimento | C13: Moderado | D13: Desenvolvimento | E13: 0.1
B14: =$C$9&"-"&D14 -> Moderado-Hotelarias | C14: Moderado | D14: Hotelarias | E14: 0.1
B15: =$C$15&"-"&D15 -> Agressivo-Papel | C15: Agressivo | D15: Papel | E15: 0.5
B16: =$C$15&"-"&D16 -> Agressivo-Tijolo | C16: Agressivo | D16: Tijolo | E16: 0.1
B17: =$C$15&"-"&D17 -> Agressivo-Híbridos | C17: Agressivo | D17: Híbridos | E17: 0.05
B18: =$C$15&"-"&D18 -> Agressivo-FOFs | C18: Agressivo | D18: FOFs | E18: 0.05
B19: =$C$15&"-"&D19 -> Agressivo-Desenvolvimento | C19: Agressivo | D19: Desenvolvimento | E19: 0.2
B20: =$C$15&"-"&D20 -> Agressivo-Hotelarias | C20: Agressivo | D20: Hotelarias | E20: 0.1
